time_travel_debugger/__init__.py
time_travel_debugger/debugger.py
time_travel_debugger-0.1.1.dist-info/License.txt
time_travel_debugger-0.1.1.dist-info/METADATA
time_travel_debugger-0.1.1.dist-info/WHEEL
time_travel_debugger-0.1.1.dist-info/top_level.txt
time_travel_debugger-0.1.1.dist-info/RECORD
