Metadata-Version: 2.1
Name: time-travel-debugger
Version: 0.1.1
Summary: A time-travel debugger for Python with step-backward execution.
Home-page: https://github.com/sddhantjaiii/Time-Travel-debugger
Author: Siddhant Jaiswal
Author-email: sddhantjaiii@gmail.com
Classifier: Programming Language :: Python :: 3
Classifier: License :: OSI Approved :: MIT License
Classifier: Operating System :: OS Independent
Requires-Python: >=3.6
License-File: License.txt
Requires-Dist: rich
